{
  "id": "contact",
  "label": "Contact",
  "icon": "fa-envelope",
  "description": "Page Contact avec en-tête, formulaire, coordonnées, carte et FAQ",
  "blocks": [
    {
      "type": "prefait-pageheader-centre-gradient",
      "props": {
        "kicker": "Contact",
        "title": "Parlons de votre projet",
        "subtitle": "Une question, un projet ou simplement envie d'échanger ? Nous sommes là pour vous."
      }
    },
    {
      "type": "prefait-contact-formulaire-split",
      "props": {
        "kicker": "Écrivez-nous",
        "title": "Envoyez-nous un message",
        "subtitle": "Nous vous répondons sous 24h ouvrées."
      }
    },
    {
      "type": "prefait-contact-coordonnees",
      "props": {
        "kicker": "Nos coordonnées",
        "title": "Comment nous joindre",
        "subtitle": "Plusieurs canaux à votre disposition.",
        "email": "contact@exemple.fr",
        "phone": "+33 1 23 45 67 89",
        "address": "10 rue de la République, 75001 Paris"
      }
    },
    {
      "type": "prefait-map-carte-info",
      "props": {
        "kicker": "Nous trouver",
        "title": "Notre adresse",
        "subtitle": "Au cœur de Paris, accessible en métro et en RER."
      }
    },
    {
      "type": "prefait-faq-2-colonnes",
      "props": {
        "kicker": "FAQ",
        "title": "Questions fréquentes",
        "subtitle": "Les réponses aux questions les plus posées."
      }
    }
  ]
}
